install_agent/__init__.py
install_agent-0.2.0.dist-info/METADATA
install_agent-0.2.0.dist-info/WHEEL
install_agent-0.2.0.dist-info/entry_points.txt
install_agent-0.2.0.dist-info/RECORD
