Metadata-Version: 2.4
Name: install-agent
Version: 0.2.0
Summary: Install Claude Code sub-agents from GitHub to your project
License-Expression: MIT
Requires-Python: >=3.10
Requires-Dist: agent-resources>=0.1.0
